pycookiecheat/__init__.py
pycookiecheat/pycookiecheat.py
pycookiecheat_slack-0.5.2.dist-info/METADATA
pycookiecheat_slack-0.5.2.dist-info/WHEEL
pycookiecheat_slack-0.5.2.dist-info/top_level.txt
pycookiecheat_slack-0.5.2.dist-info/RECORD
