Metadata-Version: 2.1
Name: pycookiecheat-slack
Version: 0.5.2
Summary: Borrow cookies from your browser's authenticated session for use in Python scripts.
Home-page: https://github.com/hraftery/pycookiecheat
Author: Heath Raftery
Author-email: heath@empirical.ee
License: MIT
Keywords: pycookiecheat chrome chromium slack cookies
Classifier: Natural Language :: English
Classifier: Programming Language :: Python :: 3
Classifier: Programming Language :: Python :: 3.7
Classifier: Programming Language :: Python :: 3.8
Classifier: Programming Language :: Python :: 3.9
Requires-Dist: cryptography (==3.4.6)
Requires-Dist: keyring (==23.0.0)
Provides-Extra: dev
Requires-Dist: build (==0.6.0.post1) ; extra == 'dev'
Requires-Dist: twine (==3.4.2) ; extra == 'dev'
Requires-Dist: wheel (==0.37.0) ; extra == 'dev'
Provides-Extra: test
Requires-Dist: black (==21.7b0) ; extra == 'test'
Requires-Dist: flake8-docstrings (==1.5.0) ; extra == 'test'
Requires-Dist: flake8-import-order (==0.18.1) ; extra == 'test'
Requires-Dist: flake8 (==3.8.4) ; extra == 'test'
Requires-Dist: mypy (==0.812) ; extra == 'test'
Requires-Dist: pep8-naming (==0.11.1) ; extra == 'test'
Requires-Dist: playwright (==1.14.1) ; extra == 'test'
Requires-Dist: pycodestyle (==2.6.0) ; extra == 'test'
Requires-Dist: pylint (==2.7.2) ; extra == 'test'
Requires-Dist: pytest (==6.2.3) ; extra == 'test'
Requires-Dist: tox (==3.23.0) ; extra == 'test'
